BeginnersbookJavaShiliChuyi/README.md
BeginnersbookJavaShiliChuyi/__init__.py
BeginnersbookJavaShiliChuyi/__main__.py
BeginnersbookJavaShiliChuyi/file.epub
BeginnersbookJavaShiliChuyi/index.html
BeginnersbookJavaShiliChuyi/css/__init__.py
BeginnersbookJavaShiliChuyi/css/annotations.css
BeginnersbookJavaShiliChuyi/css/main.css
BeginnersbookJavaShiliChuyi/css/normalize.css
BeginnersbookJavaShiliChuyi/css/popup.css
BeginnersbookJavaShiliChuyi/font/__init__.py
BeginnersbookJavaShiliChuyi/font/fontello.eot
BeginnersbookJavaShiliChuyi/font/fontello.svg
BeginnersbookJavaShiliChuyi/font/fontello.ttf
BeginnersbookJavaShiliChuyi/font/fontello.woff
BeginnersbookJavaShiliChuyi/img/__init__.py
BeginnersbookJavaShiliChuyi/img/annotator-glyph-sprite.png
BeginnersbookJavaShiliChuyi/img/annotator-icon-sprite.png
BeginnersbookJavaShiliChuyi/img/apple-touch-icon.png
BeginnersbookJavaShiliChuyi/img/cancelfullscreen.png
BeginnersbookJavaShiliChuyi/img/close.png
BeginnersbookJavaShiliChuyi/img/fullscreen.png
BeginnersbookJavaShiliChuyi/img/loader.gif
BeginnersbookJavaShiliChuyi/img/menu-icon.png
BeginnersbookJavaShiliChuyi/img/save.png
BeginnersbookJavaShiliChuyi/img/saved.png
BeginnersbookJavaShiliChuyi/img/settings-s.png
BeginnersbookJavaShiliChuyi/img/settings.png
BeginnersbookJavaShiliChuyi/img/star.png
BeginnersbookJavaShiliChuyi/js/__init__.py
BeginnersbookJavaShiliChuyi/js/epub.js
BeginnersbookJavaShiliChuyi/js/epub.min.js
BeginnersbookJavaShiliChuyi/js/epub.min.map
BeginnersbookJavaShiliChuyi/js/hooks.min.js
BeginnersbookJavaShiliChuyi/js/hooks.min.map
BeginnersbookJavaShiliChuyi/js/reader.js
BeginnersbookJavaShiliChuyi/js/reader.js.map
BeginnersbookJavaShiliChuyi/js/reader.min.js
BeginnersbookJavaShiliChuyi/js/reader.min.map
BeginnersbookJavaShiliChuyi/js/hooks/__init__.py
BeginnersbookJavaShiliChuyi/js/hooks/extensions/__init__.py
BeginnersbookJavaShiliChuyi/js/hooks/extensions/highlight.js
BeginnersbookJavaShiliChuyi/js/libs/__init__.py
beginnersbook_java_shili_chuyi-2024.3.4.0.dist-info/METADATA
beginnersbook_java_shili_chuyi-2024.3.4.0.dist-info/WHEEL
beginnersbook_java_shili_chuyi-2024.3.4.0.dist-info/entry_points.txt
beginnersbook_java_shili_chuyi-2024.3.4.0.dist-info/top_level.txt
beginnersbook_java_shili_chuyi-2024.3.4.0.dist-info/RECORD
